hmd_lib_librarian_client/__init__.py
hmd_lib_librarian_client/artifact_tools.py
hmd_lib_librarian_client/file_uploader.py
hmd_lib_librarian_client/hmd_lib_librarian_client.py
hmd_lib_librarian_client-0.1.107.dist-info/METADATA
hmd_lib_librarian_client-0.1.107.dist-info/WHEEL
hmd_lib_librarian_client-0.1.107.dist-info/top_level.txt
hmd_lib_librarian_client-0.1.107.dist-info/RECORD
